tucpdf/__init__.py
tucpdf/pdf2image.py
tucpdf/pdf2text.py
tucpdf-2.0.dist-info/Licence
tucpdf-2.0.dist-info/METADATA
tucpdf-2.0.dist-info/WHEEL
tucpdf-2.0.dist-info/top_level.txt
tucpdf-2.0.dist-info/RECORD
