Metadata-Version: 2.1
Name: tucpdf
Version: 2.0
Summary: This is a test project to convert pdf to text.
Home-page: UNKNOWN
Author: UNKNOWN
Author-email: UNKNOWN
License: UNKNOWN
Platform: UNKNOWN
